[
  {"id": "ABE", "name": "Aberdeen"},
  {"id": "ALB", "name": "Albany-Rensselaer"},
  {"id": "ALX", "name": "Alexandria"},
  {"id": "AMS", "name": "Amsterdam"},
  {"id": "BWI", "name": "Baltimore Airport"},
  {"id": "BAL", "name": "Baltimore Penn"},
  {"id": "BBY", "name": "Boston Back Bay"},
  {"id": "BOS", "name": "Boston South"},
  {"id": "BRP", "name": "Bridgeport"},
  {"id": "BUF", "name": "Buffalo-Depew"},
  {"id": "BFX", "name": "Buffalo-Exchange Street"},
  {"id": "CVS", "name": "Charlottesville"},
  {"id": "CRT", "name": "Croton-Harmon"},
  {"id": "CLP", "name": "Culpeper"},
  {"id": "ELT", "name": "Elizabethtown"},
  {"id": "FBG", "name": "Fredericksburg"},
  {"id": "HAR", "name": "Harrisburg"},
  {"id": "HUD", "name": "Hudson"},
  {"id": "KIN", "name": "Kingston"},
  {"id": "LNC", "name": "Lancaster"},
  {"id": "LYH", "name": "Lynchburg-Kemper Street"},
  {"id": "MSS", "name": "Manassas"},
  {"id": "MET", "name": "Metropark"},
  {"id": "MYS", "name": "Mystic"},
  {"id": "NBK", "name": "New Brunswick"},
  {"id": "NCR", "name": "New Carrollton"},
  {"id": "NHV", "name": "New Haven Union"},
  {"id": "NLC", "name": "New London"},
  {"id": "NRO", "name": "New Rochelle"},
  {"id": "EWR", "name": "Newark Airport"},
  {"id": "NWK", "name": "Newark Penn"},
  {"id": "NPN", "name": "Newport News"},
  {"id": "NFL", "name": "Niagara Falls"},
  {"id": "OSB", "name": "Old Saybrook"},
  {"id": "PAO", "name": "Paoli"},
  {"id": "PTB", "name": "Petersburg"},
  {"id": "PHL", "name": "Philadelphia 30th Street"},
  {"id": "PGH", "name": "Pittsburgh"},
  {"id": "POU", "name": "Poughkeepsie"},
  {"id": "PJC", "name": "Princeton Junction"},
  {"id": "PVD", "name": "Providence"},
  {"id": "QAN", "name": "Quantico"},
  {"id": "RHI", "name": "Rhinecliff-Kingston"},
  {"id": "RVM", "name": "Richmond Main Street"},
  {"id": "RVR", "name": "Richmond Staples Mill Road"},
  {"id": "ROC", "name": "Rochester"},
  {"id": "ROM", "name": "Rome"},
  {"id": "SDY", "name": "Schenectady"},
  {"id": "STM", "name": "Stamford"},
  {"id": "SYR", "name": "Syracuse"},
  {"id": "TRE", "name": "Trenton"},
  {"id": "UCA", "name": "Utica"},
  {"id": "WAS", "name": "Washington Union"},
  {"id": "RTE", "name": "Westwood-Route 128"},
  {"id": "WBG", "name": "Williamsburg"},
  {"id": "WIL", "name": "Wilmington"},
  {"id": "YNY", "name": "Yonkers"}
]
